{"frontknowledge_common_image.md":"bxusgUop","cssnotes_01.md":"D6w58wZm","frontknowledge_common_upload.md":"y_KD0i6w","cssnotes_09.md":"R2eZ_qYF","browserknowledge_03.md":"AlPaES_R","databaseknowledge_01.md":"MI-9rdni","frontknowledge_other_01.md":"BaX1eklo","datavisualizationknowledge_03.md":"v4g5jBTY","browsernotes_01.md":"vh4iA_TT","frontknowledge_basicmethod_paging.md":"5gQNwQTn","eslintnotes_01.md":"hoHZk2mn","exercise_01.md":"ONqt26t-","java_redis_01.md":"ahGe-M9j","cssknowledge_01.md":"kr-oOXtZ","cssnotes_04.md":"ZoHmYDet","cssknowledge_03.md":"k3bneG5c","androidnotes_01.md":"Rio1QlKx","frontknowledge_basicmethod_axios.md":"_UtoRHYY","frontknowledge_opensourceprojects_readme.md":"OwJfwnAU","browserknowledge_01.md":"4lYc8520","cssnotes_06.md":"cwHL8JB2","cssnotes_02.md":"NfmLMRIj","java_maven_01.md":"kiJLV0sZ","frontknowledge_git_git.md":"2zfXpumH","cssnotes_08.md":"sB1h-014","cssnotes_05.md":"PPfBl6kz","cssnotes_07.md":"Xy5A69Ir","frontknowledge_git_command.md":"677c4F7L","cssnotes_03.md":"UUamL560","frontknowledge_monitor_readme.md":"2ctTC_ay","frontknowledge_basicmethod_promisic.md":"BjdVkSpU","databaseknowledge_02.md":"u0t7CHN2","databasenotes_01.md":"ddwrlIGx","datavisualizationknowledge_05.md":"zaDwjTWR","frontknowledge_other_02.md":"lVEYZRik","frontknowledge_other_03.md":"ZtFf5hnc","browsernotes_02.md":"ogKAwdLP","cssknowledge_02.md":"EikndzNZ","frontknowledge_other_04.md":"OK9LnCl_","datavisualizationknowledge_04.md":"pyLW2Is4","java_nginx_01.md":"txnHm5Xc","java_nginx_02.md":"W_HOwqQK","eslintnotes_02.md":"tRAEbOzI","datavisualizationknowledge_01.md":"8Qr8o8OZ","httpnotes_01.md":"xmr3TrYU","frontknowledge_utils_regexp.md":"gpO7SjQv","index.md":"VTVxEy7S","browserknowledge_02.md":"IKg8T7BB","frontknowledge_utils_method.md":"3QNBE6Xe","datavisualizationknowledge_02.md":"lJTUpGT1","java_maven_02.md":"_NY6uEQ4","java_utils_method.md":"HvfE2Q3M","java_tomcat_01.md":"jD43VXNn","javaknowledge_11.md":"sJn5c8m6","java_springboot_pagination.md":"XYxJ-py6","javaknowledge_02.md":"ZRtyL0ru","miniprogramnotes_07.md":"uq1Vm63J","miniprogramnotes_08.md":"IOdois1e","miniprogramnotes_09.md":"QC3GqnjD","miniprogramnotes_10.md":"HZV8rie3","miniprogramnotes_11.md":"TqFMQGEy","miniprogramnotes_12.md":"vN23VR_2","javaknowledge_32.md":"G1NAtodB","javaknowledge_07.md":"gq71xlGi","miniprogramnotes_05.md":"h_D72n7f","nodeknowledge_02.md":"KX67lF4S","miniprogramnotes_06.md":"U4f8f4gL","springbootnotes_02.md":"C4TZvhFX","springbootnotes_03.md":"Tx5wf9um","springbootnotes_05.md":"WuLTl7Zs","springbootnotes_06.md":"1P9gHP9v","vueknowledge_05.md":"ByfiPXCj","springbootnotes_04.md":"_qsDbuYS","jsknowledge_10.md":"KE-t0f-V","springbootnotes_08.md":"WTFmbF09","javanotes_07.md":"t0ddpl7c","javaknowledge_05.md":"PESqbqKM","jetbrainsnotes_01.md":"pRHv3rTo","jetbrainsnotes_02.md":"rNUPIv6i","jetbrainsnotes_03.md":"VRAvtdZV","jetbrainsnotes_04.md":"kehgaG0Z","jetbrainsnotes_05.md":"8HOwAT3A","jetbrainsnotes_06.md":"WUzrCoDd","jsknowledge_01.md":"d3mMYUiV","jsknowledge_02.md":"W17BePik","jsknowledge_03.md":"hr0zzP8m","javaknowledge_19.md":"Arb89jEO","jsknowledge_04.md":"YZ7S4oWK","javaknowledge_33.md":"rBATA3Ub","javaknowledge_34.md":"5NKLO0qB","javanotes_03.md":"sL838q6V","typescriptnotes_02.md":"n_tm3TTF","typescriptnotes_03.md":"Nk4pNMQB","javaknowledge_30.md":"Y0SY7ztn","typescriptnotes_04.md":"pEYgaTFO","uniappnotes_01.md":"ExFBtNUA","uniappnotes_06.md":"rQ1UnsKu","mavennotes_02.md":"-rsX2X2Z","vitenotes_04.md":"fTrXRecS","vue_basiccomponent_date.md":"tEyO-0h9","vue_basiccomponent_footer.md":"A7KMv9Lc","datavisualizationknowledge_06.md":"Pr2gaQa3","vuenotes_20.md":"KqSajxel","javaknowledge_01.md":"-1s9alqK","vueknowledge_15.md":"uxiwCe1O","vuenotes_23.md":"9jMlcYmL","vuenotes_26.md":"kLByOL3V","vuenotes_27.md":"38Y3bHmp","vueknowledge_16.md":"GJ1PBQyw","javaknowledge_28.md":"tyaA2MGD","webpackknowledge_02.md":"OgiqbZXD","webpackknowledge_01.md":"vqqDCZsN","vuenotes_28.md":"PUih3lIh","vuenotes_30.md":"2UHi8RkR","vuepressnotes_02.md":"szlCq_GN","vuenotes_02.md":"YUeOYexV","vuenotes_03.md":"LwtP9F9i","vuenotes_19.md":"D3WT1P39","vuenotes_07.md":"gULFCBDk","vuenotes_09.md":"r3tjIzTF","vuenotes_13.md":"0UJKVXZp","vuenotes_14.md":"BoFrVJuB","vuenotes_16.md":"0TD1fC_u","vuenotes_04.md":"3pFx-Kit","javaknowledge_12.md":"IUmYoZht","javaknowledge_22.md":"bexEk7sY","jsknowledge_06.md":"zcDWFcOh","webpackknowledge_04.md":"0LyXP6Vm","vuenotes_01.md":"2ulNMKxG","webpackknowledge_03.md":"lKQd9aiX","javaknowledge_03.md":"D-qFgRop","vitenotes_02.md":"tzXuf1pF","jsknowledge_12.md":"k96UwSxe","uniappnotes_02.md":"qvC8ISzx","uniappnotes_03.md":"svw5Tq3g","jsknowledge_13.md":"WvfJy3q1","uniappnotes_05.md":"EjPnRNIu","jsknowledge_16.md":"TQuVwCKd","jsnotes_01.md":"Hn46liXK","jsnotes_03.md":"nA6qhfh4","jsknowledge_17.md":"mCN_Tmu6","uniappnotes_08.md":"q5vgPkGI","jsnotes_04.md":"GdagnoRB","jsnotes_02.md":"R2lKYMVM","jsnotes_05.md":"FO2UOOQM","jsnotes_07.md":"IrVR7PEf","vitenotes_01.md":"LRVrMFss","mavennotes_01.md":"HvmCNkFB","miniprogramnotes_01.md":"NwQAUfJJ","jsnotes_08.md":"HyJawLlF","vitenotes_05.md":"DrpWAR-y","miniprogramnotes_02.md":"bWIPJfWx","vitenotes_03.md":"veP2x88w","miniprogramnotes_03.md":"3DqWaJYq","javaknowledge_08.md":"JSpuKn75","javaknowledge_20.md":"MEevDHn5","miniprogramnotes_04.md":"Ghdzjn-H","nodeknowledge_01.md":"IPA5zI5y","javaknowledge_09.md":"kDEur56E","mybatisknowledge_01.md":"WIluG-LI","javaknowledge_16.md":"TcgqZb-z","javaknowledge_25.md":"FjkhYr7H","javaknowledge_24.md":"Ew2N98W6","javaknowledge_13.md":"N3gVOUcQ","mybatisknowledge_02.md":"4zMKHXSs","nodeknowledge_03.md":"FGw3G6vQ","javaknowledge_14.md":"jfA8_Sm1","javaknowledge_06.md":"q5Hs78_f","javanotes_04.md":"ICSYqKd8","vueknowledge_02.md":"5vSTEJjs","jsknowledge_07.md":"0fp1ntpe","scaffold_01.md":"rKSQhbhf","vueknowledge_03.md":"ih63OTh3","scaffold_02.md":"cpBJZx0H","vueknowledge_04.md":"9Ahrmvld","javaknowledge_10.md":"GVE-e0E8","vuenotes_05.md":"QgkHPWh7","javaknowledge_04.md":"w1vbbTNt","vue_basiccomponent_slide.md":"eQhDbzHL","vue_directive_loading.md":"DaTEvxd1","javaknowledge_36.md":"PcWtJV4N","vue_basiccomponent_ruler.md":"StoyKZr3","javaknowledge_18.md":"ip2zwq81","jsnotes_06.md":"A-C_pmV0","uniappnotes_07.md":"7eUSijJ-","jsknowledge_14.md":"ltmEzlM9","springbootnotes_07.md":"QchEWVpy","uniappnotes_04.md":"yHUvfPNh","microfrontknowledge_01.md":"xTJZFccX","javanotes_05.md":"KVdsdglk","javanotes_06.md":"eIbcXJdR","vuenotes_06.md":"POpIsGBA","vuenotes_12.md":"hTb1ezb9","vuenotes_15.md":"DSrmLbk0","javaknowledge_31.md":"39gePMSV","vuenotes_22.md":"7oX6IOrS","vue_basiccomponent_loading.md":"EDojUuX5","vuenotes_29.md":"iqUJZ_nl","javaknowledge_35.md":"mdD87RGP","jsknowledge_05.md":"YyVxMYM5","vuenotes_24.md":"6xZ86E25","vue_directive_permission.md":"iH5i3_sr","vue_basiccomponent_svg.md":"cmw9omTN","vue_plugin_good-storage.md":"it0BKtlR","vueknowledge_08.md":"kJjoVMYY","vueknowledge_06.md":"qEROG9ht","vueknowledge_07.md":"ZY3HeG2f","javaknowledge_15.md":"j-tb7Gra","javaknowledge_23.md":"yNABItGX","jsknowledge_15.md":"yS9Xprn1","javaknowledge_27.md":"5JvxCkRY","vuenotes_18.md":"cod9eHVQ","vue_plugin_crypto-js.md":"hf-wlhkZ","jsknowledge_11.md":"HU5TF6P0","java_springboot_swagger.md":"QOZtmoFZ","javanotes_02.md":"ErSIUjgl","vuenotes_08.md":"PJGxxTVo","javaknowledge_17.md":"H2EkFgRK","vuenotes_25.md":"17T7bMkJ","vuenotes_21.md":"rlAtQpJu","vuenotes_11.md":"SABfzfSt","vuenotes_10.md":"hTTcHqME","jsknowledge_08.md":"1i3uwEL1","vuepressnotes_01.md":"5rEhybQW","vue_globalcomponent_button.md":"G37Db8JY","vueknowledge_10.md":"78BOk6qv","springbootnotes_01.md":"mFzgP7rH","javanotes_01.md":"Djee5Ile","vue_basiccomponent_scroll.md":"c6QiCH21","vueknowledge_01.md":"oLNoHnxl","javaknowledge_21.md":"8n-80xKt","vueknowledge_14.md":"IhxnNlYY","vue_eslint.md":"EMDolDRT","vueknowledge_12.md":"iP7z8r6B","vueknowledge_13.md":"O7-g_0S1","vue_basiccomponent_imagelazy.md":"xYQxR1Ei","vueknowledge_09.md":"zp7soC50","javaknowledge_26.md":"AABBZvjI","typescriptnotes_01.md":"DdTYzv06","jsknowledge_09.md":"5UUhaXWt","vuenotes_17.md":"r0dzNyQH","javaknowledge_29.md":"re95Ief1","vueknowledge_11.md":"VndAtISo"}
