{"cssknowledge_03.md":"mby6be09","cssnotes_08.md":"SuPeN5dL","browserknowledge_02.md":"yuYYNYS9","exercise_01.md":"n_30-nxD","cssnotes_07.md":"yu4LZHUd","eslintnotes_01.md":"lQfTfVNK","cssnotes_09.md":"tm7281u5","httpnotes_01.md":"yazG-A0z","cssknowledge_01.md":"w4UfVNpe","index.md":"i_FIUXLN","androidnotes_01.md":"lBSI354R","datavisualizationknowledge_06.md":"9O42QS6z","databaseknowledge_01.md":"u8qnZLHM","frontknowledge_other_04.md":"SHZZ_r5v","cssnotes_05.md":"j6A_orhy","cssnotes_04.md":"sUtcQWj1","browsernotes_02.md":"u4oIXuwh","frontknowledge_other_02.md":"iUDHp5WA","frontknowledge_monitor_readme.md":"uySRscd3","frontknowledge_common_image.md":"kWqS6Wdw","frontknowledge_common_upload.md":"N6QteecF","datavisualizationknowledge_04.md":"fBAR0Hhk","eslintnotes_02.md":"QaPPP467","java_maven_01.md":"mzf5FDV8","java_maven_02.md":"R6q1wwb1","browserknowledge_03.md":"GJ60Kzph","datavisualizationknowledge_01.md":"x2bLskkP","cssnotes_03.md":"t-jNwHcM","cssnotes_02.md":"e2VHkGyQ","cssnotes_06.md":"wrwaBOAh","cssnotes_01.md":"TZqqtnbf","frontknowledge_git_git.md":"Zn31fBXd","datavisualizationknowledge_03.md":"YAm32xi8","datavisualizationknowledge_05.md":"YzVOvWth","datavisualizationknowledge_02.md":"0VWK2SX7","databaseknowledge_02.md":"yBW2DVx1","frontknowledge_utils_regexp.md":"kWmkMTD0","frontknowledge_other_03.md":"iYF8Hlg5","databasenotes_01.md":"1wz3cO76","browserknowledge_01.md":"REcH9pQ2","frontknowledge_basicmethod_paging.md":"TPWLY-Jj","frontknowledge_other_01.md":"P96cyrjo","frontknowledge_utils_method.md":"zFTWKHf2","browsernotes_01.md":"cgLd84Ze","frontknowledge_basicmethod_promisic.md":"2aQEJIcl","frontknowledge_opensourceprojects_readme.md":"WJQbfdrF","javaknowledge_14.md":"tBMp44ku","java_utils_method.md":"Wqfh40iJ","javaknowledge_02.md":"C99RZzAR","javaknowledge_03.md":"yutFxaln","javaknowledge_04.md":"WWFHEbOj","javaknowledge_05.md":"zVtWHtwg","javaknowledge_06.md":"YVrY_ooS","javaknowledge_07.md":"9vpr5zEL","frontknowledge_basicmethod_axios.md":"cOUGNt9V","java_nginx_01.md":"8_-HIe7l","javaknowledge_08.md":"Fel1L6K6","javaknowledge_17.md":"FztbbUWG","jsnotes_02.md":"8yaTAlId","jsnotes_06.md":"TB9evTmm","javaknowledge_11.md":"oeN4bgTH","javaknowledge_10.md":"IdjAMP3I","cssknowledge_02.md":"a4pFpQtX","jsknowledge_08.md":"omel8XOb","jsknowledge_09.md":"GB-ufFfJ","javaknowledge_18.md":"ZFD4OFLF","javaknowledge_19.md":"3nVxn6aP","javaknowledge_20.md":"5ER1Pszz","javaknowledge_21.md":"mlIYeQFI","javaknowledge_22.md":"banoJGnB","javaknowledge_23.md":"y9uCU_3d","javaknowledge_24.md":"ccZewDgC","miniprogramnotes_01.md":"v2BDWTZO","javaknowledge_34.md":"26pg2wRL","javaknowledge_27.md":"j0srBRWl","javaknowledge_35.md":"SSsHNoiA","javanotes_01.md":"fHamvaQg","javanotes_03.md":"-cqFviac","javanotes_04.md":"1YMGMksr","javanotes_05.md":"E-b8hvij","javaknowledge_09.md":"Ip7A7HWB","javanotes_07.md":"A9oy0C0h","jetbrainsnotes_01.md":"ceYeoNN9","jetbrainsnotes_02.md":"Xy7Hmq6b","jetbrainsnotes_03.md":"wdZ8FwJl","jsknowledge_01.md":"qSmblh0J","jsknowledge_02.md":"8x6Rcb_N","jsknowledge_03.md":"HN99D6k_","javaknowledge_33.md":"cblHTXPj","jsknowledge_04.md":"5MR6dZxM","javanotes_02.md":"SMZR5JYg","javanotes_06.md":"scX-pfiZ","jsnotes_05.md":"t24Firs_","javaknowledge_16.md":"DaPAsGh2","javaknowledge_28.md":"gIsXxBGj","javaknowledge_26.md":"CHaqcw9Q","javaknowledge_25.md":"cEtphd2X","javaknowledge_31.md":"YrQq7teP","jsnotes_01.md":"7F8DeeI-","javaknowledge_13.md":"NF5HTvDc","javaknowledge_32.md":"rVGjIB8v","javaknowledge_29.md":"mMdS4uB1","javaknowledge_15.md":"0RpDqUuT","jsknowledge_06.md":"e7i1T44a","vueknowledge_09.md":"70nZOrzp","jsknowledge_07.md":"81wB087s","mybatisknowledge_01.md":"c3VPHo9U","miniprogramnotes_05.md":"l_dD2v7g","miniprogramnotes_06.md":"crhlIpvS","frontknowledge_git_command.md":"bUzbn9F5","miniprogramnotes_07.md":"QosOjez8","miniprogramnotes_08.md":"Jrkqcd10","miniprogramnotes_09.md":"XE7upkq7","miniprogramnotes_10.md":"8fb0SCic","miniprogramnotes_11.md":"MnCejcS2","java_springboot_pagination.md":"bmbr3cZp","jsnotes_03.md":"qtJN-O2S","miniprogramnotes_12.md":"RGs8cyBA","springbootnotes_02.md":"ulLnstZQ","springbootnotes_03.md":"VMk_opxl","springbootnotes_04.md":"249AVIN2","springbootnotes_05.md":"zeywUQEW","springbootnotes_06.md":"SncZgCew","springbootnotes_07.md":"4auQ0Pra","springbootnotes_08.md":"01kGFGkn","typescriptnotes_01.md":"dC5OMvEm","typescriptnotes_02.md":"Z13Umqcm","typescriptnotes_03.md":"phiVKomw","typescriptnotes_04.md":"s19hDabu","vue_eslint.md":"9mG4cSJT","uniappnotes_01.md":"kB14KaSg","uniappnotes_02.md":"ArTgdJAe","uniappnotes_03.md":"D15j26bb","uniappnotes_04.md":"7yIXgSKB","uniappnotes_05.md":"1GDQimSF","uniappnotes_06.md":"NQHagx7j","vue_globalcomponent_button.md":"VHiDTgi-","jsnotes_04.md":"P4dwuYYU","springbootnotes_01.md":"9S3DNR8X","uniappnotes_08.md":"ZaCG--PL","vitenotes_01.md":"oVqTeb4v","vitenotes_02.md":"FUC0iOd4","vitenotes_03.md":"craG6yuk","vitenotes_04.md":"XmuZPAWG","vitenotes_05.md":"X6o3MQS1","vue_basiccomponent_date.md":"TEob9Iy8","vue_basiccomponent_footer.md":"_uggp2tx","vue_basiccomponent_imagelazy.md":"f6uye1VM","vue_directive_loading.md":"smvsXfnm","vue_plugin_crypto-js.md":"GFdbottc","mybatisknowledge_02.md":"Bkm6sdG3","nodeknowledge_01.md":"H87SMro3","vue_basiccomponent_svg.md":"uZ3DZriF","vueknowledge_06.md":"FY1NQ4ZM","vue_plugin_good-storage.md":"Iip6fdiy","vue_directive_permission.md":"R6frzZvH","vue_basiccomponent_loading.md":"Bk4NJqcI","vuenotes_08.md":"USci_dML","vueknowledge_02.md":"qSc75xT5","vueknowledge_01.md":"hZkbt3uk","vueknowledge_04.md":"CMKxeJ0W","java_tomcat_01.md":"KIL52K1L","java_nginx_02.md":"OQwwP7MT","vueknowledge_07.md":"6roZ02Qs","java_redis_01.md":"xm129ySv","vueknowledge_08.md":"bPM3DHME","vue_basiccomponent_slide.md":"lvoZDhpk","java_springboot_swagger.md":"JGemU1mt","jsknowledge_13.md":"eSXg0R_B","nodeknowledge_02.md":"NfdebpCu","javaknowledge_12.md":"kUBEwRUE","vueknowledge_10.md":"czBhPfzD","jsknowledge_12.md":"tvB5jx8Y","nodeknowledge_03.md":"LSFmyeK9","scaffold_01.md":"lrCgmViY","scaffold_02.md":"1Sg4i2ke","vueknowledge_03.md":"Rgbs9P6-","vueknowledge_05.md":"YZTkwhON","vue_basiccomponent_scroll.md":"zc2Anfs-","jsknowledge_11.md":"0uu1Usnz","miniprogramnotes_02.md":"ytW9ebfr","jsknowledge_05.md":"8i2AtC4e","jsnotes_08.md":"29WAS85Y","jsknowledge_17.md":"gpW6Pye8","vueknowledge_11.md":"VyoC6FnP","mavennotes_01.md":"MxFRaOzb","jsknowledge_14.md":"rV0V2Muf","uniappnotes_07.md":"cGfEc9Rv","jsknowledge_16.md":"uHQMeG4X","mavennotes_02.md":"A-laob_Z","microfrontknowledge_01.md":"kSUv-rhK","jsknowledge_15.md":"-euPmqLK","jsnotes_07.md":"jNvQOpB4","miniprogramnotes_03.md":"dIra0m1h","miniprogramnotes_04.md":"iXrLIBCp","webpackknowledge_03.md":"_xUGy4Er","vueknowledge_12.md":"h8KOBPpa","vueknowledge_14.md":"3zrq75an","vueknowledge_13.md":"QStSgXDx","webpackknowledge_04.md":"UuCE-NN-","vuenotes_20.md":"5j3lOvYv","vuenotes_19.md":"PtQpokKV","javaknowledge_30.md":"ahbxtWSD","vuenotes_21.md":"FWTPXxim","vuenotes_22.md":"nz8ZXmzm","vuenotes_23.md":"MMTbtrXI","vuenotes_24.md":"1u3MKr_r","vuenotes_25.md":"E6NelmbA","vuenotes_26.md":"9PM7XcXH","vuenotes_27.md":"Mb89Ssiw","vuenotes_29.md":"6f_N442f","vuenotes_28.md":"WYLK1t4a","vuenotes_30.md":"nZKBfOeo","vuepressnotes_01.md":"uZfW2CVe","webpackknowledge_01.md":"AC-XKqOZ","vuenotes_10.md":"GQGEaa3R","vuepressnotes_02.md":"erwIaFqv","vuenotes_04.md":"cT636kLW","webpackknowledge_02.md":"KMCdQWZb","vueknowledge_15.md":"M2QTC5qj","vueknowledge_16.md":"v8qeNNeU","vuenotes_01.md":"Xm-NubPL","vuenotes_02.md":"tqfCeTM-","vuenotes_03.md":"D_0elc4i","vuenotes_11.md":"j_CvOnvm","vuenotes_16.md":"RpNY365G","vuenotes_05.md":"T2mAd8Sv","vuenotes_12.md":"VoHJydLr","vuenotes_13.md":"4pbiEvTt","vuenotes_14.md":"gVx4cHkM","vuenotes_15.md":"WeiPpRCc","vuenotes_07.md":"dZtMFFAI","vuenotes_06.md":"VsIW_69E","vuenotes_09.md":"p2ZJuMCf","vuenotes_17.md":"ctUN6mPf","vue_basiccomponent_ruler.md":"6yB3TpFi","javaknowledge_01.md":"5X2Cuxme","jsknowledge_10.md":"wmPkasdZ","vuenotes_18.md":"vnzQHT82"}
