{"browsernotes_02.md":"VuFZSpVK","browserknowledge_02.md":"IILg5Ikc","jsnotes_07.md":"sLAtvxR0","jsnotes_08.md":"-rvqgniz","miniprogramnotes_03.md":"OhtYzETh","miniprogramnotes_04.md":"GWz2uypF","miniprogramnotes_05.md":"clAgpTNL","miniprogramnotes_07.md":"XCOGP1MQ","miniprogramnotes_02.md":"4Lq3Q8kF","miniprogramnotes_08.md":"F2lWJLgm","nodeknowledge_01.md":"sOxuEBGg","scaffold_01.md":"wV3PB0aK","scaffold_02.md":"iP86Wl4p","springbootnotes_01.md":"EjMckqR9","springbootnotes_02.md":"aCQsH86r","springbootnotes_03.md":"XRw8z9CQ","springbootnotes_04.md":"409him4y","springbootnotes_05.md":"zi2nYg6H","datavisualizationknowledge_03.md":"zaalVGnR","eslintnotes_02.md":"2AFWArdj","exercise_01.md":"z7Q2X13C","javaknowledge_09.md":"9khj8D1A","cssnotes_05.md":"ufhE8VD6","vuenotes_28.md":"uKaBjTWi","jsknowledge_06.md":"vgycY9LK","cssnotes_07.md":"ZZwcgnXA","javaknowledge_16.md":"Qq76j1NF","springbootnotes_06.md":"KUVQEhbZ","browserknowledge_03.md":"91cXyj3T","nodeknowledge_02.md":"TqeA7wo6","cssnotes_04.md":"ryA0aLTK","springbootnotes_08.md":"gTxUlFjV","typescriptnotes_01.md":"zlYLrlyz","typescriptnotes_02.md":"olOYG_TK","typescriptnotes_04.md":"K_yY9CrJ","uniappnotes_01.md":"be_5LPLm","uniappnotes_02.md":"e9KemqM3","uniappnotes_03.md":"FB7BflFh","uniappnotes_04.md":"vSmQs8BK","uniappnotes_08.md":"AtrrXP-b","vitenotes_01.md":"dMbdiOzv","cssknowledge_02.md":"ZrjMrXpE","typescriptnotes_03.md":"LVWtZjra","vue_basiccomponent_svg.md":"bAcyHMZ1","vitenotes_03.md":"s7-XHVc8","javanotes_07.md":"bsUTkINj","cssnotes_01.md":"bSu1WoHp","jsknowledge_09.md":"tkDTnenb","jsknowledge_10.md":"wrO9tRIN","javaknowledge_14.md":"RzYKtf_y","jsknowledge_13.md":"WcfU_Zo2","jsknowledge_14.md":"xSmgPYpg","jsknowledge_15.md":"e4VjSOeS","frontknowledge_monitor_readme.md":"bKR_PKxJ","javaknowledge_13.md":"ALrlHjOm","uniappnotes_07.md":"IH5Zy9TJ","datavisualizationknowledge_05.md":"DcBQNOWe","vue_basiccomponent_imagelazy.md":"nwrhcbsw","vue_basiccomponent_loading.md":"5KFoVA9Q","frontknowledge_other_03.md":"2MGdUcG-","jsknowledge_01.md":"4NYMCuQ0","frontknowledge_other_01.md":"uz2Od3KY","frontknowledge_other_02.md":"4P-I8Eff","java_springboot_swagger.md":"TOQANuVM","miniprogramnotes_06.md":"kucqe_JS","java_utils_method.md":"WSq0LYsg","androidnotes_01.md":"oegKrXOT","cssnotes_09.md":"PRSfp8jf","javaknowledge_03.md":"eiLBeAGU","javaknowledge_04.md":"9m3p35YK","javaknowledge_07.md":"F1iK3PlA","cssknowledge_01.md":"LrH17oOS","java_maven_02.md":"QWKJNs1B","browserknowledge_01.md":"crD9WQyr","jsknowledge_12.md":"T63DtL6-","javanotes_03.md":"q9Kj0HMf","mavennotes_02.md":"48h2CxKU","microfrontknowledge_01.md":"f1Dq82Y9","miniprogramnotes_01.md":"IpdpR84o","browsernotes_01.md":"umSWdczv","jsknowledge_17.md":"r0fePHwf","vue_basiccomponent_ruler.md":"E8ybhGm3","mavennotes_01.md":"x-vd55xi","frontknowledge_opensourceprojects_readme.md":"tzp6-5LL","vuenotes_08.md":"bvZonwME","javaknowledge_06.md":"g3miMhph","datavisualizationknowledge_04.md":"ikAXEpuf","vuenotes_05.md":"k9LpaGgm","jsknowledge_11.md":"TZIgANxV","cssknowledge_03.md":"FIaJHmyb","uniappnotes_05.md":"bUhHA9GV","jsnotes_01.md":"psbpe1uq","vue_directive_permission.md":"O20cQvMC","vue_directive_loading.md":"n7x7AINi","vuenotes_23.md":"N3jkddX_","vuenotes_17.md":"kLPL4Akn","vue_eslint.md":"mqEnX_Gk","vuenotes_14.md":"Z-rrmS39","vuenotes_01.md":"mrlJN6AP","java_nginx_01.md":"bi2AWOq0","vuenotes_02.md":"UQB93VRD","vitenotes_04.md":"yxnLubn_","vuenotes_03.md":"fOLx30Jv","vuenotes_04.md":"TMRfO78B","javaknowledge_11.md":"h_yIvFaa","httpnotes_01.md":"gWfb-yBl","frontknowledge_common_upload.md":"-v6ZJbeC","databaseknowledge_01.md":"fN-chuMO","javaknowledge_12.md":"hbf5y7P_","javaknowledge_08.md":"UlKPdD1O","java_maven_01.md":"PF3dmUHo","webpackknowledge_02.md":"WyT5cGzJ","jetbrainsnotes_02.md":"mPvAqvwn","vuepressnotes_02.md":"pbbA5Nvs","webpackknowledge_01.md":"zH29abRf","vuepressnotes_01.md":"MDBKY_6F","vuenotes_29.md":"_RZoWzQk","vuenotes_30.md":"C-zn6NVy","jsnotes_03.md":"iOAldG10","jsnotes_02.md":"xQhL0GXn","jsknowledge_02.md":"gc0dwHC2","webpackknowledge_03.md":"3xjMZE9V","webpackknowledge_04.md":"-9wgay10","miniprogramnotes_10.md":"LXLEYnSv","miniprogramnotes_11.md":"r8R3kE-k","eslintnotes_01.md":"fPoMAwz_","jsknowledge_16.md":"ltwHZOb1","miniprogramnotes_12.md":"IzJqPUWW","javaknowledge_17.md":"gizXW9D0","datavisualizationknowledge_02.md":"aDuhjJAV","frontknowledge_utils_regexp.md":"o_Z4US1b","miniprogramnotes_09.md":"Gn1OBuwr","vue_plugin_crypto-js.md":"1ojdjs-6","javaknowledge_18.md":"04opnPYB","frontknowledge_other_04.md":"oY0nafnf","cssnotes_06.md":"D6KTDhnK","datavisualizationknowledge_06.md":"6AuRw1Gs","java_nginx_02.md":"khLksA73","frontknowledge_utils_method.md":"yS2_Rip8","mybatisknowledge_01.md":"9cj9qeVU","index.md":"mUHQnr4G","frontknowledge_basicmethod_paging.md":"CjRgdoKi","java_springboot_pagination.md":"q5KRQOlG","javaknowledge_02.md":"GbInm5ny","vuenotes_06.md":"P-XNIrA1","mybatisknowledge_02.md":"LP95438U","vuenotes_07.md":"gxa0kUeI","vueknowledge_03.md":"Cgt_n-Nm","vueknowledge_04.md":"e7SlEgpM","vueknowledge_05.md":"0IvrtG6f","jsnotes_04.md":"vIPHdini","java_tomcat_01.md":"3s2bPnyQ","jsknowledge_07.md":"mG6R0Gke","vueknowledge_07.md":"8eFCe9N-","frontknowledge_basicmethod_promisic.md":"mmCIHWQn","vueknowledge_08.md":"9Kw4ioka","jetbrainsnotes_03.md":"sHGVn3G3","springbootnotes_07.md":"M5Z1DZZD","vueknowledge_09.md":"AnwAqqFi","vueknowledge_12.md":"LCNd3oSW","cssnotes_03.md":"4DqyiEMo","uniappnotes_06.md":"uypM-SKQ","vueknowledge_10.md":"8msiyLnq","javanotes_05.md":"cyJJocFe","javanotes_06.md":"io5ZlNGr","javanotes_04.md":"qMAxgrzc","cssnotes_08.md":"7hT272zy","vueknowledge_13.md":"nhIlT2OW","vue_basiccomponent_slide.md":"cdBuHzaQ","java_redis_01.md":"p33h-jDv","frontknowledge_common_image.md":"tonC-1-Y","javaknowledge_20.md":"OA7_qP5G","javaknowledge_10.md":"SHLw38Me","cssnotes_02.md":"wJ7PLaFF","javaknowledge_21.md":"Ayw1mVMK","frontknowledge_git_git.md":"VcckKct1","javaknowledge_15.md":"PAPMtM84","javaknowledge_22.md":"P5zNGcZ2","vueknowledge_16.md":"Kz6_A1mO","javaknowledge_23.md":"UFQOj1Nr","javaknowledge_24.md":"NNlArj29","javaknowledge_05.md":"G2q112N4","javaknowledge_29.md":"nki80Bmz","vitenotes_02.md":"amnsGnLD","javanotes_01.md":"2uM2gruv","javanotes_02.md":"COTC1_JZ","javaknowledge_32.md":"aQDuq6RH","vueknowledge_15.md":"2XSkiytW","jsknowledge_05.md":"zQ-gY2D9","javaknowledge_25.md":"HlM6XxJL","javaknowledge_30.md":"wi0uqz7V","jsknowledge_04.md":"W8FlJDjY","vitenotes_05.md":"5eGGitCv","frontknowledge_git_command.md":"oqbUw2N5","vue_plugin_good-storage.md":"M28tnLwW","javaknowledge_31.md":"ecseLTpH","javaknowledge_01.md":"MOyWMHlL","javaknowledge_28.md":"Rf7zqc6Q","vue_basiccomponent_scroll.md":"4C7LkZjG","vue_globalcomponent_button.md":"Hv3BYrPQ","vueknowledge_01.md":"KlH_-S09","vueknowledge_02.md":"Bvp5OL_E","vueknowledge_14.md":"erKocEIJ","javaknowledge_19.md":"qOpQM20r","jsnotes_05.md":"D9-7hmYM","jsnotes_06.md":"jDWR0UBH","vueknowledge_11.md":"3nk_ojpD","datavisualizationknowledge_01.md":"c5XRALrU","jetbrainsnotes_01.md":"XbcVD7Up","vuenotes_09.md":"kRqtOO-V","vuenotes_10.md":"hCt-22w4","vuenotes_11.md":"6BbJNHeB","vuenotes_24.md":"F_briR-f","vuenotes_12.md":"vQFUoKvG","vue_basiccomponent_footer.md":"mHHNkI3D","vuenotes_18.md":"lqoB-S9N","vuenotes_19.md":"asAAlUdU","vuenotes_20.md":"XO_4YH6x","vuenotes_22.md":"9heFAI6I","vuenotes_21.md":"uFO837vw","vuenotes_25.md":"SHwN_3XJ","frontknowledge_basicmethod_axios.md":"WZKTpEc2","vuenotes_26.md":"I1-KiRjy","javaknowledge_26.md":"c-UsmK-H","jsknowledge_08.md":"JNQw-UH5","vuenotes_27.md":"RO5ZpAuS","javaknowledge_27.md":"CyUVq-PH","jsknowledge_03.md":"4AJ6adin","vueknowledge_06.md":"B8beNMm_","vuenotes_13.md":"kAxHX5PN","vuenotes_15.md":"zRAkWDU2","vuenotes_16.md":"TfQqh_Hr"}
